jables/__init__.py
jables/apps.py
jables/models.py
django_jables-1.0.dist-info/LICENSE
django_jables-1.0.dist-info/METADATA
django_jables-1.0.dist-info/WHEEL
django_jables-1.0.dist-info/top_level.txt
django_jables-1.0.dist-info/RECORD
